tetrimino/__about__.py
tetrimino/__init__.py
tetrimino-0.0.1.dist-info/METADATA
tetrimino-0.0.1.dist-info/WHEEL
tetrimino-0.0.1.dist-info/licenses/LICENSE.txt
tetrimino-0.0.1.dist-info/RECORD
